{"cameraMode":{"drawMode":0,"name":"Shaded","section":"Shading Mode"},"sceneLighting":false,"audioPlay":false,"sceneViewState":{"showFog":true,"showMaterialUpdate":false,"showSkybox":false,"showFlares":true,"showImageEffects":true,"showParticleSystems":true},"in2DMode":false,"pivot":{"x":-0.04905503988265991,"y":0.7397371530532837,"z":0.06695429980754852},"rotation":{"x":-0.023001618683338167,"y":0.976997435092926,"z":-0.15096789598464967,"w":-0.14885714650154115},"size":9.25788402557373,"orthographic":false}